metasub_utils.wasabi-0.8.0-py3.6-nspkg.pth
metasub_utils/wasabi/__init__.py
metasub_utils/wasabi/cli.py
metasub_utils/wasabi/constants.py
metasub_utils/wasabi/metasub_public_files.txt
metasub_utils/wasabi/public_files.py
metasub_utils/wasabi/wasabi_bucket.py
metasub_utils.wasabi-0.8.0.dist-info/METADATA
metasub_utils.wasabi-0.8.0.dist-info/RECORD
metasub_utils.wasabi-0.8.0.dist-info/WHEEL
metasub_utils.wasabi-0.8.0.dist-info/entry_points.txt
metasub_utils.wasabi-0.8.0.dist-info/namespace_packages.txt
metasub_utils.wasabi-0.8.0.dist-info/top_level.txt
