Metadata-Version: 2.1
Name: metasub-utils.wasabi
Version: 0.8.0
Summary: UNKNOWN
Home-page: UNKNOWN
Author: David Danko
Author-email: dcdanko@gmail.com
License: MIT license
Platform: UNKNOWN
Classifier: License :: OSI Approved :: MIT License
Classifier: Natural Language :: English
Classifier: Programming Language :: Python :: 3.6
Requires-Dist: metasub-utils.metadata
Requires-Dist: boto3
Requires-Dist: awscli
Requires-Dist: click
